pyjones/__init__.py
pyjones/opticalelements.py
pyjones/polarizations.py
pyjones-0.6.0.dist-info/LICENSE
pyjones-0.6.0.dist-info/METADATA
pyjones-0.6.0.dist-info/WHEEL
pyjones-0.6.0.dist-info/top_level.txt
pyjones-0.6.0.dist-info/RECORD
